[
	{
		"company_product_name" : "MacBook Pro"
	},
	{
		"company_product_name" : "MacBook"
	},
	{
		"company_product_name" : "MacBook Air"
	},
	{
		"company_product_name" : "iMac"
	},
	{
		"company_product_name" : "Apple TV"
	},
	{
		"company_product_name" : "iPod Classic"
	},
	{
		"company_product_name" : "iPad 2,3, or 4"
	},
	{
		"company_product_name" : "iPad Mini"
	},
	{
		"company_product_name" : "iPad Air"
	},
	{
		"company_product_name" : "iPhone 6"
	},
	{
		"company_product_name" : "iPhone 6S"
	},
	{
		"company_product_name" : "iPhone 6S Plus"
	},
	{
		"company_product_name" : "iPhone 7"
	},
	{
		"company_product_name" : "iPhone 7 Plus"
	},
	{
		"company_product_name" : "Airpods"
	},
	{
		"company_product_name" : "Apple Watch"
	},
	{
		"company_product_name" : "iPod Shuffle"
	},
	{
		"company_product_name" : "Android"
	},
	{
		"company_product_name" : "Google Assistant"
	},
	{
		"company_product_name" : "Google Base "
	},
	{
		"company_product_name" : "Google Calendar"
	},
	{
		"company_product_name" : "Google Cars"
	},
	{
		"company_product_name" : "Google Chrome"
	},
	{
		"company_product_name" : "Google Chromecast"
	},
	{
		"company_product_name" : "Google Chromebook"
	},
	{
		"company_product_name" : "Google Code"
	},
	{
		"company_product_name" : "GCP"
	},
	{
		"company_product_name" : "Google Classroom"
	},
	{
		"company_product_name" : "Google Dashboard"
	},
	{
		"company_product_name" : "Google Docs"
	},
	{
		"company_product_name" : "Google Express"
	},
	{
		"company_product_name" : "Google Fiber"
	},
	{
		"company_product_name" : "Google Flights"
	},
	{
		"company_product_name" : "Google Groups"
	},
	{
		"company_product_name" : "Google Hangouts"
	},
	{
		"company_product_name" : "Google Hire"
	},
	{
		"company_product_name" : "Google Inbox"
	},
	{
		"company_product_name" : "Google Mail"
	},
	{
		"company_product_name" : "Google Mobile"
	},
	{
		"company_product_name" : "Google Nexus"
	},
	{
		"company_product_name" : "Google OnHub "
	},
	{
		"company_product_name" : "Google Patents"
	},
	{
		"company_product_name" : "Google Pay"
	},
	{
		"company_product_name" : "Google Photos"
	},
	{
		"company_product_name" : "Google Play"
	},
	{
		"company_product_name" : "vSphere"
	},
	{
		"company_product_name" : "vCenter Server"
	},
	{
		"company_product_name" : "VMware Enterprise PKS"
	},
	{
		"company_product_name" : "vSphere Integrated Containers"
	},
	{
		"company_product_name" : "vCloud Director"
	},
	{
		"company_product_name" : "NSX Data Center"
	},
	{
		"company_product_name" : "NSX Cloud"
	},
	{
		"company_product_name" : "vRealize Network Insight"
	},
	{
		"company_product_name" : "VMware HCX"
	},
	{
		"company_product_name" : "AppDefense"
	},
	{
		"company_product_name" : "vSAN"
	},
	{
		"company_product_name" : "Site Recovery Manager"
	},
	{
		"company_product_name" : "VMware Site Recovery"
	},
	{
		"company_product_name" : "Virtual Volumes"
	},
	{
		"company_product_name" : "Dell EMC VxRail"
	},
	{
		"company_product_name" : "vRealize Suite"
	},
	{
		"company_product_name" : "vCloud Suite"
	},
	{
		"company_product_name" : "Wavefront by VMware"
	},
	{
		"company_product_name" : "Workspace ONE"
	},
	{
		"company_product_name" : "Amazon Athena"
	},
	{
		"company_product_name" : "Amazon EMR"
	},
	{
		"company_product_name" : "Amazon Redshift"
	},
	{
		"company_product_name" : "Amazon Kinesis"
	},
	{
		"company_product_name" : "Amazon Quicksight"
	},
	{
		"company_product_name" : "AWS Glue"
	},
	{
		"company_product_name" : "AWS Data Lake"
	},
	{
		"company_product_name" : "Amazon CloudWatch"
	},
	{
		"company_product_name" : "Amazon EC2"
	},
	{
		"company_product_name" : "AWS Batch"
	},
	{
		"company_product_name" : "AWS Lambda"
	},
	{
		"company_product_name" : "AWS Elastic Search"
	},
	{
		"company_product_name" : "AWS Fargate"
	},
	{
		"company_product_name" : "Amazon LightSail"
	},
	{
		"company_product_name" : "Amazon RDS"
	},
	{
		"company_product_name" : "Amazon Timestream"
	},
	{
		"company_product_name" : "Amazon Aurora"
	},
	{
		"company_product_name" : "Amazon Dynamo DB"
	},
	{
		"company_product_name" : "AWS Iot Core"
	},
	{
		"company_product_name" : "Ambari"
	},
	{
		"company_product_name" : "Aurora"
	},
	{
		"company_product_name" : "Airflow"
	},
	{
		"company_product_name" : "Cassandra"
	},
	{
		"company_product_name" : "Camel"
	},
	{
		"company_product_name" : "CloudStack"
	},
	{
		"company_product_name" : "CouchDB"
	},
	{
		"company_product_name" : "Derby"
	},
	{
		"company_product_name" : "Directory"
	},
	{
		"company_product_name" : "Drill"
	},
	{
		"company_product_name" : "Dubbo"
	},
	{
		"company_product_name" : "Eagle"
	},
	{
		"company_product_name" : "Flix"
	},
	{
		"company_product_name" : "Flume"
	},
	{
		"company_product_name" : "Hadoop"
	},
	{
		"company_product_name" : "HBase"
	},
	{
		"company_product_name" : "Kafka"
	},
	{
		"company_product_name" : "Zoopkeeper"
	},
	{
		"company_product_name" : "Oozie"
	}
]
